soutools/__init__.py
soutools/controller.py
soutools/helpers.py
soutools/main.py
soutools/menu.py
soutools/model.py
soutools/settings.py
soutools-0.0.5.dist-info/LICENSE
soutools-0.0.5.dist-info/METADATA
soutools-0.0.5.dist-info/WHEEL
soutools-0.0.5.dist-info/entry_points.txt
soutools-0.0.5.dist-info/top_level.txt
soutools-0.0.5.dist-info/RECORD
